<?xml version='1.0' encoding='utf-8'?>
<Gesture Name="left_curly_brace06" Subject="0" Number="6" NumPts="231" Millseconds="2615"><Point X="229.0" Y="-454.0" T="25717" /><Point X="227.0" Y="-454.0" T="25725" /><Point X="226.0" Y="-454.0" T="25732" /><Point X="225.0" Y="-453.0" T="25739" /><Point X="222.0" Y="-453.0" T="25746" /><Point X="221.0" Y="-450.0" T="25753" /><Point X="216.0" Y="-449.0" T="25760" /><Point X="214.0" Y="-447.0" T="25767" /><Point X="211.0" Y="-445.0" T="25773" /><Point X="206.0" Y="-438.0" T="25780" /><Point X="201.0" Y="-431.0" T="25788" /><Point X="196.0" Y="-426.0" T="25796" /><Point X="192.0" Y="-417.0" T="25802" /><Point X="185.0" Y="-410.0" T="25809" /><Point X="182.0" Y="-404.0" T="25816" /><Point X="179.0" Y="-399.0" T="25824" /><Point X="177.0" Y="-395.0" T="25831" /><Point X="175.0" Y="-392.0" T="25839" /><Point X="173.0" Y="-387.0" T="25844" /><Point X="170.0" Y="-386.0" T="25851" /><Point X="169.0" Y="-385.0" T="25859" /><Point X="168.0" Y="-382.0" T="25873" /><Point X="168.0" Y="-381.0" T="25880" /><Point X="167.0" Y="-380.0" T="25886" /><Point X="167.0" Y="-379.0" T="25894" /><Point X="166.0" Y="-376.0" T="25908" /><Point X="166.0" Y="-375.0" T="25915" /><Point X="166.0" Y="-374.0" T="25922" /><Point X="166.0" Y="-372.0" T="25935" /><Point X="166.0" Y="-369.0" T="25942" /><Point X="167.0" Y="-368.0" T="25951" /><Point X="168.0" Y="-366.0" T="25957" /><Point X="169.0" Y="-363.0" T="25964" /><Point X="172.0" Y="-362.0" T="25972" /><Point X="174.0" Y="-359.0" T="25978" /><Point X="175.0" Y="-356.0" T="25985" /><Point X="175.0" Y="-355.0" T="25991" /><Point X="176.0" Y="-353.0" T="26000" /><Point X="176.0" Y="-351.0" T="26006" /><Point X="176.0" Y="-348.0" T="26014" /><Point X="177.0" Y="-346.0" T="26022" /><Point X="177.0" Y="-345.0" T="26027" /><Point X="178.0" Y="-344.0" T="26034" /><Point X="178.0" Y="-343.0" T="26041" /><Point X="178.0" Y="-342.0" T="26049" /><Point X="178.0" Y="-341.0" T="26056" /><Point X="180.0" Y="-340.0" T="26063" /><Point X="180.0" Y="-337.0" T="26070" /><Point X="180.0" Y="-336.0" T="26077" /><Point X="180.0" Y="-334.0" T="26093" /><Point X="181.0" Y="-332.0" T="26099" /><Point X="181.0" Y="-330.0" T="26105" /><Point X="181.0" Y="-329.0" T="26112" /><Point X="181.0" Y="-328.0" T="26119" /><Point X="182.0" Y="-325.0" T="26126" /><Point X="182.0" Y="-323.0" T="26133" /><Point X="182.0" Y="-320.0" T="26140" /><Point X="185.0" Y="-319.0" T="26147" /><Point X="185.0" Y="-316.0" T="26155" /><Point X="185.0" Y="-312.0" T="26161" /><Point X="186.0" Y="-309.0" T="26168" /><Point X="186.0" Y="-307.0" T="26175" /><Point X="187.0" Y="-304.0" T="26183" /><Point X="187.0" Y="-300.0" T="26189" /><Point X="187.0" Y="-295.0" T="26197" /><Point X="187.0" Y="-293.0" T="26204" /><Point X="187.0" Y="-292.0" T="26211" /><Point X="189.0" Y="-291.0" T="26217" /><Point X="189.0" Y="-288.0" T="26232" /><Point X="189.0" Y="-287.0" T="26247" /><Point X="189.0" Y="-286.0" T="26253" /><Point X="189.0" Y="-283.0" T="26267" /><Point X="189.0" Y="-282.0" T="26282" /><Point X="189.0" Y="-281.0" T="26302" /><Point X="189.0" Y="-280.0" T="26316" /><Point X="189.0" Y="-279.0" T="26338" /><Point X="189.0" Y="-278.0" T="26351" /><Point X="189.0" Y="-277.0" T="26366" /><Point X="188.0" Y="-275.0" T="26380" /><Point X="188.0" Y="-274.0" T="26401" /><Point X="187.0" Y="-272.0" T="26415" /><Point X="187.0" Y="-271.0" T="26429" /><Point X="186.0" Y="-271.0" T="26443" /><Point X="186.0" Y="-270.0" T="26465" /><Point X="184.0" Y="-270.0" T="26478" /><Point X="184.0" Y="-268.0" T="26500" /><Point X="182.0" Y="-268.0" T="26528" /><Point X="181.0" Y="-268.0" T="26676" /><Point X="180.0" Y="-268.0" T="26711" /><Point X="179.0" Y="-268.0" T="26717" /><Point X="179.0" Y="-267.0" T="26733" /><Point X="178.0" Y="-267.0" T="26739" /><Point X="177.0" Y="-266.0" T="26747" /><Point X="176.0" Y="-265.0" T="26754" /><Point X="172.0" Y="-265.0" T="26761" /><Point X="171.0" Y="-264.0" T="26767" /><Point X="168.0" Y="-260.0" T="26775" /><Point X="165.0" Y="-259.0" T="26782" /><Point X="161.0" Y="-256.0" T="26789" /><Point X="154.0" Y="-252.0" T="26796" /><Point X="150.0" Y="-248.0" T="26802" /><Point X="145.0" Y="-243.0" T="26811" /><Point X="136.0" Y="-238.0" T="26817" /><Point X="131.0" Y="-233.0" T="26824" /><Point X="122.0" Y="-229.0" T="26831" /><Point X="118.0" Y="-225.0" T="26838" /><Point X="115.0" Y="-223.0" T="26846" /><Point X="108.0" Y="-220.0" T="26852" /><Point X="106.0" Y="-219.0" T="26860" /><Point X="103.0" Y="-217.0" T="26867" /><Point X="102.0" Y="-217.0" T="26874" /><Point X="99.0" Y="-216.0" T="26888" /><Point X="98.0" Y="-216.0" T="26894" /><Point X="96.0" Y="-216.0" T="26916" /><Point X="95.0" Y="-216.0" T="26937" /><Point X="93.0" Y="-216.0" T="26972" /><Point X="92.0" Y="-216.0" T="27007" /><Point X="91.0" Y="-216.0" T="27022" /><Point X="91.0" Y="-217.0" T="27057" /><Point X="91.0" Y="-219.0" T="27092" /><Point X="91.0" Y="-220.0" T="27106" /><Point X="92.0" Y="-220.0" T="27113" /><Point X="94.0" Y="-221.0" T="27120" /><Point X="95.0" Y="-222.0" T="27127" /><Point X="97.0" Y="-222.0" T="27134" /><Point X="98.0" Y="-222.0" T="27142" /><Point X="100.0" Y="-224.0" T="27149" /><Point X="101.0" Y="-224.0" T="27155" /><Point X="102.0" Y="-226.0" T="27163" /><Point X="103.0" Y="-227.0" T="27168" /><Point X="104.0" Y="-227.0" T="27183" /><Point X="107.0" Y="-227.0" T="27190" /><Point X="109.0" Y="-228.0" T="27204" /><Point X="110.0" Y="-228.0" T="27212" /><Point X="112.0" Y="-229.0" T="27227" /><Point X="113.0" Y="-229.0" T="27234" /><Point X="114.0" Y="-229.0" T="27241" /><Point X="115.0" Y="-229.0" T="27247" /><Point X="117.0" Y="-229.0" T="27254" /><Point X="119.0" Y="-229.0" T="27261" /><Point X="122.0" Y="-229.0" T="27267" /><Point X="125.0" Y="-229.0" T="27276" /><Point X="128.0" Y="-229.0" T="27283" /><Point X="130.0" Y="-227.0" T="27290" /><Point X="135.0" Y="-226.0" T="27297" /><Point X="139.0" Y="-226.0" T="27303" /><Point X="143.0" Y="-225.0" T="27310" /><Point X="146.0" Y="-222.0" T="27317" /><Point X="152.0" Y="-222.0" T="27325" /><Point X="155.0" Y="-220.0" T="27331" /><Point X="158.0" Y="-219.0" T="27339" /><Point X="159.0" Y="-219.0" T="27346" /><Point X="163.0" Y="-218.0" T="27353" /><Point X="164.0" Y="-218.0" T="27359" /><Point X="165.0" Y="-218.0" T="27374" /><Point X="166.0" Y="-218.0" T="27381" /><Point X="166.0" Y="-217.0" T="27388" /><Point X="167.0" Y="-217.0" T="27409" /><Point X="168.0" Y="-215.0" T="27444" /><Point X="170.0" Y="-214.0" T="27480" /><Point X="171.0" Y="-213.0" T="27507" /><Point X="171.0" Y="-212.0" T="27515" /><Point X="172.0" Y="-212.0" T="27549" /><Point X="172.0" Y="-210.0" T="27586" /><Point X="172.0" Y="-208.0" T="27622" /><Point X="172.0" Y="-207.0" T="27641" /><Point X="172.0" Y="-206.0" T="27656" /><Point X="172.0" Y="-204.0" T="27663" /><Point X="171.0" Y="-203.0" T="27670" /><Point X="171.0" Y="-200.0" T="27677" /><Point X="169.0" Y="-196.0" T="27684" /><Point X="169.0" Y="-191.0" T="27691" /><Point X="168.0" Y="-185.0" T="27698" /><Point X="168.0" Y="-177.0" T="27705" /><Point X="168.0" Y="-171.0" T="27712" /><Point X="168.0" Y="-161.0" T="27719" /><Point X="168.0" Y="-155.0" T="27726" /><Point X="168.0" Y="-145.0" T="27733" /><Point X="168.0" Y="-137.0" T="27741" /><Point X="168.0" Y="-125.0" T="27748" /><Point X="168.0" Y="-115.0" T="27754" /><Point X="168.0" Y="-99.0" T="27761" /><Point X="170.0" Y="-85.0" T="27768" /><Point X="170.0" Y="-74.0" T="27775" /><Point X="172.0" Y="-63.0" T="27783" /><Point X="174.0" Y="-54.0" T="27790" /><Point X="178.0" Y="-45.0" T="27796" /><Point X="178.0" Y="-41.0" T="27804" /><Point X="179.0" Y="-38.0" T="27810" /><Point X="179.0" Y="-35.0" T="27818" /><Point X="179.0" Y="-34.0" T="27839" /><Point X="179.0" Y="-33.0" T="27917" /><Point X="180.0" Y="-33.0" T="27952" /><Point X="181.0" Y="-33.0" T="27973" /><Point X="181.0" Y="-34.0" T="28008" /><Point X="181.0" Y="-37.0" T="28021" /><Point X="182.0" Y="-37.0" T="28029" /><Point X="182.0" Y="-38.0" T="28043" /><Point X="184.0" Y="-39.0" T="28050" /><Point X="184.0" Y="-40.0" T="28057" /><Point X="185.0" Y="-41.0" T="28071" /><Point X="186.0" Y="-43.0" T="28079" /><Point X="186.0" Y="-44.0" T="28085" /><Point X="187.0" Y="-44.0" T="28092" /><Point X="189.0" Y="-45.0" T="28100" /><Point X="191.0" Y="-46.0" T="28106" /><Point X="192.0" Y="-49.0" T="28121" /><Point X="193.0" Y="-50.0" T="28128" /><Point X="194.0" Y="-51.0" T="28142" /><Point X="194.0" Y="-52.0" T="28148" /><Point X="195.0" Y="-52.0" T="28162" /><Point X="196.0" Y="-53.0" T="28177" /><Point X="198.0" Y="-54.0" T="28184" /><Point X="199.0" Y="-55.0" T="28191" /><Point X="201.0" Y="-55.0" T="28198" /><Point X="201.0" Y="-57.0" T="28205" /><Point X="202.0" Y="-57.0" T="28212" /><Point X="203.0" Y="-58.0" T="28219" /><Point X="205.0" Y="-60.0" T="28233" /><Point X="206.0" Y="-60.0" T="28241" /><Point X="206.0" Y="-61.0" T="28248" /><Point X="207.0" Y="-62.0" T="28255" /><Point X="208.0" Y="-62.0" T="28262" /><Point X="208.0" Y="-64.0" T="28268" /><Point X="209.0" Y="-64.0" T="28276" /><Point X="209.0" Y="-65.0" T="28282" /><Point X="210.0" Y="-65.0" T="28290" /><Point X="210.0" Y="-66.0" T="28304" /><Point X="211.0" Y="-66.0" T="28311" /><Point X="211.0" Y="-67.0" T="28332" /></Gesture>